<?xml version="1.0" encoding="UTF-8"?>
<package name="tablaCatalogoFotos" extends="struts-default, json-default">
    <action name="testCatalogoFotos" class="CatalogoFotos" method="consultarTodos">
        <result>/TestCatalogoFotos.jsp</result>
    </action>
    <action name="eliminarCatalogoFotos" class="CatalogoFotos" method="eliminar">
        <result type="redirectAction">testCatalogoFotos</result>
    </action>
    <action name="consultarCatalogoFotos" class="CatalogoFotos" method="consultarUnico">
        <result >/test/TestCatalogoFotos.jsp</result>
    </action>
    <action name="guardarCatalogoFotos" class="CatalogoFotos" method="guardar">
        <result>/test/TestCatalogoFotos.jsp</result>
    </action>
    <action name="editarCatalogoFotos" class="CatalogoFotos" method="editar">
        <result type="redirectAction">testCatalogoFotos</result>
    </action>
</package>

<package name="tablaCategoria" extends="struts-default, json-default">
    <action name="testCategoria" class="Categoria" method="consultarTodos">
        <result>/test/TestCategoria.jsp</result>
    </action>
    <action name="eliminarCategoria" class="Categoria" method="eliminar">
        <result type="redirectAction">testCategoria</result>
    </action>
    <action name="consultarCategoria" class="Categoria" method="consultarUnico">
        <result >/roles/Administrador/PanelAdministrador.jsp</result>
    </action>
    <action name="guardarCategoria" class="Categoria" method="guardar">
        <result type="json"></result>
    </action>
    <action name="editarCategoria" class="Categoria" method="editar">
        <result type="redirectAction">testCategoria</result>
    </action>
    <action name="consultarCategoriasJson" class="Direcciones" method="consultarCategorias">
        <result type="json"></result>
    </action>
</package>

<package name="tablaCodigoPostal" extends="struts-default, json-default">
    <action name="testCodigoPostal" class="CodigoPostal" method="consultarTodos">
        <result>/test/TestCodigoPostal.jsp</result>
    </action>
    <action name="eliminarCodigoPostal" class="CodigoPostal" method="eliminar">
        <result type="redirectAction">testCodigoPostal</result>
    </action>
    <action name="consultarCodigoPostal" class="CodigoPostal" method="consultarUnico">
        <result >/test/TestCodigoPostal.jsp</result>
    </action>
    <action name="guardarCodigoPostal" class="CodigoPostal" method="guardar">
        <result type="redirectAction">testCodigoPostal</result>
    </action>
    <action name="guardarCodigoPostalJson" class="CodigoPostal" method="guardar">
        <result type="json"></result>
    </action>
    <action name="editarCodigoPostal" class="CodigoPostal" method="editar">
        <result type="redirectAction">testCodigoPostal</result>
    </action> 
</package>

<package name="tablaColonia" extends="struts-default, json-default">
    <action name="testColonia" class="Colonia" method="consultarTodos">
        <result>/test/TestColonia.jsp</result>
    </action>
    <action name="eliminarColonia" class="Colonia" method="eliminar">
        <result type="redirectAction">testColonia</result>
    </action>
    <action name="consultarColonia" class="Colonia" method="consultarUnico">
        <result >/test/TestColonia.jsp</result>
    </action>
    <action name="guardarColonia" class="Colonia" method="guardar">
        <result type="redirectAction">testColonia</result>
    </action>
    <action name="editarColonia" class="Colonia" method="editar">
        <result type="redirectAction">testColonia</result>
    </action>
    <action name="consultarColoniasJson" class="Colonia" method="consultarTodos">
        <result type="json"></result>
    </action>
    <action name="guardarColoniaJson" class="Colonia" method="guardar">
        <result type="json"></result>
    </action>
</package>

<package name="tablaContrato" extends="struts-default, json-default">
    <action name="testContrato" class="Contrato" method="consultarTodos">
        <result>/test/TestContrato.jsp</result>
    </action>
    <action name="eliminarContrato" class="Contrato" method="eliminar">
        <result type="redirectAction">testContrato</result>
    </action>
    <action name="consultarContrato" class="Contrato" method="consultarUnico">
        <result >/test/TestContrato.jsp</result>
    </action>
    <action name="guardarContrato" class="Contrato" method="guardar">
        <result type="redirectAction">testContrato</result>
    </action>
    <action name="editarContrato" class="Contrato" method="editar">
        <result type="redirectAction">testContrato</result>
    </action>
    <action name="consultarUsuariosContratoJSON" class="Contrato" method="consultarUsuarios">
        <result type="json"></result>
    </action>
    <action name="consultarPropiedadesContratoJSON" class="Contrato" method="consultarPropiedades">
        <result type="json"></result>
    </action>
    <action name="consultarContratosJson" class="Contrato" method="consultarTodos">
        <result type="json"></result>
    </action>
    <action name="guardarContratoJson" class="Contrato" method="guardar">
        <result type="json"></result>
    </action>
</package>
<package name="tablaDiseniadorPropiedad" extends="struts-default">
    <action name="testDiseniadorPropiedad" class="DiseniadorPropiedad" method="consultarTodos">
        <result>/test/TestDiseniadorPropiedad.jsp</result>
    </action>
    <action name="eliminarDiseniadorPropiedad" class="DiseniadorPropiedad" method="eliminar">
        <result type="redirectAction">testDiseniadorPropiedad</result>
    </action>
    <action name="consultarDiseniadorPropiedad" class="DiseniadorPropiedad" method="consultarUnico">
        <result >/test/TestDiseniadorPropiedad.jsp</result>
    </action>
    <action name="guardarDiseniadorPropiedad" class="DiseniadorPropiedad" method="guardar">
        <result type="redirectAction">testDiseniadorPropiedad</result>
    </action>
    <action name="editarDiseniadorPropiedad" class="DiseniadorPropiedad" method="editar">
        <result type="redirectAction">testDiseniadorPropiedad</result>
    </action>
</package>

<package name="tablaDisenio" extends="struts-default, json-default">
    <action name="testDisenio" class="Disenio" method="consultarTodos">
        <result>/test/TestDisenio.jsp</result>
    </action>
    <action name="eliminarDisenio" class="Disenio" method="eliminar">
        <result type="redirectAction">testDisenio</result>
    </action>
    <action name="consultarDisenio" class="Disenio" method="consultarUnico">
        <result >/test/TestDisenio.jsp</result>
    </action>
    <action name="guardarDisenio" class="Disenio" method="guardar">
        <result>/roles/Administrador/PanelAdministrador.jsp</result>
    </action>
    <action name="editarDisenio" class="Disenio" method="editar">
        <result type="redirectAction">testDisenio</result>
    </action>
    <action name="consultarDiseniosJson" class="Disenio" method="consultarTodosJson">
        <result type="json"></result>
    </action>
</package>

<package name="tablaEstado" extends="struts-default, json-default">
    <action name="testEstado" class="Estado" method="consultarTodos">
        <result>/test/TestEstado.jsp</result>
    </action>
    <action name="eliminarEstado" class="Estado" method="eliminar">
        <result type="redirectAction">testEstado</result>
    </action>
    <action name="consultarEstado" class="Estado" method="consultarUnico">
        <result >/test/TestEstado.jsp</result>
    </action>
    <action name="guardarEstado" class="Estado" method="guardar">
        <result type="redirectAction">testEstado</result>
    </action>
    <action name="editarEstado" class="Estado" method="editar">
        <result type="redirectAction">testEstado</result>
    </action>
    <action name="consultaEstadosJson" class="Estado" method="consultarTodos">
        <result type="json"></result>
    </action>
</package>

<package name="tablaFavorito" extends="struts-default">
    <action name="testFavorito" class="Favorito" method="consultarTodos">
        <result>/test/TestFavorito.jsp</result>
    </action>
    <action name="eliminarFavorito" class="Favorito" method="eliminar">
        <result type="redirectAction">testFavorito</result>
    </action>
    <action name="consultarFavorito" class="Favorito" method="consultarUnico">
        <result>/test/TestFavorito.jsp</result>
    </action>
    <action name="guardarFavorito" class="Favorito" method="guardar">
        <result>/test/TestFavorito.jsp</result>
    </action>
    <action name="editarFavorito" class="Favorito" method="editar">
        <result type="redirectAction">testFavorito</result>
    </action>
</package>

<package name="tablaHistorial" extends="struts-default, json-default">
    <action name="testHistorial" class="Historial" method="consultarTodos">
        <result>/test/TestHistorial.jsp</result>
    </action>
    <action name="eliminarHistorial" class="Historial" method="eliminar">
        <result type="redirectAction">testHistorial</result>
    </action>
    <action name="consultarHistorial" class="Historial" method="consultarUnico">
        <result >/test/TestHistorial.jsp</result>
    </action>
    <action name="guardarHistorial" class="Historial" method="guardar">
        <result>/test/TestHistorial.jsp</result>
    </action>
    <action name="editarHistorial" class="Historial" method="editar">
        <result type="redirectAction">testHistorial</result>
    </action>
</package>

<package name="tablaLocalidad" extends="struts-default, json-default">
    <action name="testLocalidad" class="Localidad" method="consultarTodos">
        <result>/test/TestLocalidad.jsp</result>
    </action>
    <action name="eliminarLocalidad" class="Localidad" method="eliminar">
        <result type="redirectAction">testLocalidad</result>
    </action>
    <action name="consultarLocalidad" class="Localidad" method="consultarUnico">
        <result >/test/TestLocalidad.jsp</result>
    </action>
    <action name="guardarLocalidad" class="Localidad" method="guardar">
        <result type="redirectAction">testLocalidad</result>
    </action>
    <action name="editarLocalidad" class="Localidad" method="editar">
        <result type="redirectAction">testLocalidad</result>
    </action>
    <action name="guardarLocalidadJson" class="Localidad" method="guardar">
        <result type="json"></result>
    </action>
    
</package>

<package name="tablaMensaje" extends="struts-default">
    <action name="testMensaje" class="Mensaje" method="consultarTodos">
        <result>/test/TestMensaje.jsp</result>
    </action>
    <action name="eliminarMensaje" class="Mensaje" method="eliminar">
        <result type="redirectAction">testMensaje</result>
    </action>
    <action name="consultarMensaje" class="Mensaje" method="consultarUnico">
        <result >/test/TestMensaje.jsp</result>
    </action>
    <action name="guardarMensaje" class="Mensaje" method="guardar">
        <result type="redirectAction">testMensaje</result>
    </action>
    <action name="editarMensaje" class="Mensaje" method="editar">
        <result type="redirectAction">testMensaje</result>
    </action>
</package>

<package name="tablaPago" extends="struts-default, json-default">
    <action name="testPago" class="Pago" method="consultarTodos">
        <result>/test/TestPago.jsp</result>
    </action>
    <action name="eliminarPago" class="Pago" method="eliminar">
        <result type="redirectAction">testPago</result>
    </action>
    <action name="consultarPago" class="Pago" method="consultarUnico">
        <result >/test/TestPago.jsp</result>
    </action>
    <action name="guardarPago" class="Pago" method="guardar">
        <result type="redirectAction">testPago</result>
    </action>
    <action name="editarPago" class="Pago" method="editar">
        <result type="redirectAction">testPago</result>
    </action>
    <action name="consultarPagosJson" class="Pago" method="consultarTodos">
        <result type="json"></result>
    </action> 
</package>

<package name="tablaPais" extends="struts-default, json-default">
    <action name="testPais" class="Pais" method="consultarTodos">
        <result>/test/TestPais.jsp</result>
    </action>
    <action name="eliminarPais" class="Pais" method="eliminar">
        <result type="redirectAction">testPais</result>
    </action>
    <action name="consultarPais" class="Pais" method="consultarUnico">
        <result >/test/TestPais.jsp</result>
    </action>
    <action name="guardarPais" class="Pais" method="guardar">
        <result type="redirectAction">testPais</result>
    </action>
    <action name="guardarPaisJson" class="Pais" method="guardar">
        <result type="json"></result>
    </action>
    <action name="editarPais" class="Pais" method="editar">
        <result type="redirectAction">testPais</result>
    </action>
</package>

<package name="tablaPropiedad" extends="struts-default, json-default">
    <action name="testPropiedad" class="Propiedad" method="consultarTodos">
        <result>/test/TestPropiedad.jsp</result>
    </action>
    <action name="eliminarPropiedad" class="Propiedad" method="eliminar">
        <result type="redirectAction">testPropiedad</result>
    </action>
    <action name="consultarPropiedad" class="Propiedad" method="consultarUnico">
        <result >/test/TestPropiedad.jsp</result>
    </action>
    <action name="guardarPropiedad" class="Propiedad" method="guardar">
        <result type="redirectAction">testPropiedad</result>
    </action>
    <action name="editarPropiedad" class="Propiedad" method="editar">
        <result type="redirectAction">testPropiedad</result>
    </action>
    <action name="consultarPropiedadesJson" class="Propiedad" method="consultarTodos">
        <result type="json"></result>
    </action>
    <action name="guardarPropiedadJson" class="Propiedad" method="guardar">
        <result type="json"></result>
    </action>
    
</package>

<package name="tablaPublicidad" extends="struts-default, json-default">
    <action name="testPublicidad" class="Publicidad" method="consultarTodos">
        <result>/test/TestPublicidad.jsp</result>
    </action>
    <action name="eliminarPublicidad" class="Publicidad" method="eliminar">
        <result type="redirectAction">testPublicidad</result>
    </action>
    <action name="consultarPublicidad" class="Publicidad" method="consultarUnico">
        <result >/test/TestPublicidad.jsp</result>
    </action>
    <action name="guardarPublicidad" class="Publicidad" method="guardar">
        <!--        <interceptor-ref name="exception"/>
        <interceptor-ref name="i18n"/>
        <interceptor-ref name="fileUpload">
            <param name="allowedTypes">text/plain</param>
            <param name="maximumSize">10240</param>
        </interceptor-ref> 
        <interceptor-ref name="params">
            <param name="excludeParams">dojo\..*,^struts\..*</param>
        </interceptor-ref>
        <interceptor-ref name="validation">
            <param name="excludeMethods">input,back,cancel,browse</param>
        </interceptor-ref>
        <interceptor-ref name="workflow">
            <param name="excludeMethods">input,back,cancel,browse</param>
        </interceptor-ref>-->
            
        <result>/roles/Administrador/PanelAdministrador.jsp</result>
    </action>
    <action name="guardarPublicidadJson" class="Publicidad" method="guardar">
        <result type="json"></result>
    </action>
    <action name="editarPublicidad" class="Publicidad" method="editar">
        <result type="redirectAction">testPublicidad</result>
    </action>
</package>

<package name="tablaRegistroPago" extends="struts-default">
    <action name="testRegistroPago" class="RegistroPago" method="consultarTodos">
        <result>/test/TestRegistroPago.jsp</result>
    </action>
    <action name="eliminarRegistroPago" class="RegistroPago" method="eliminar">
        <result type="redirectAction">testRegistroPago</result>
    </action>
    <action name="consultarRegistroPago" class="RegistroPago" method="consultarUnico">
        <result>/test/TestRegistroPago.jsp</result>
    </action>
    <action name="guardarRegistroPago" class="RegistroPago" method="guardar">
        <result>/test/TestRegistroPago.jsp</result>
    </action>
    <action name="editarRegistroPago" class="RegistroPago" method="editar">
        <result type="redirectAction">testRegistroPago</result>
    </action>
</package>

<package name="tablaUsuario" extends="struts-default, json-default">
    <action name="testUsuario" class="Usuario" method="consultarTodos">
        <result>/test/TestUsuario.jsp</result>
    </action>
    <action name="eliminarUsuario" class="Usuario" method="eliminar">
        <result type="redirectAction">testUsuario</result>
    </action>
    <action name="consultarUsuario" class="Usuario" method="consultarUnico">
        <result >/test/TestUsuario.jsp</result>
    </action>
    <action name="guardarUsuario" class="Usuario" method="guardar">
        <result>index.jsp</result>
    </action>
    <action name="editarUsuario" class="Usuario" method="editar">
        <result type="redirectAction">testUsuario</result>
    </action>
    <action name="consultarUsuariosJson" class="Usuario" method="consultarTodos">
        <result type="json"></result>
    </action> 
    <action name="consultarDiseniadoresJson" class="Usuario" method="consultarDiseniadores">
        <result type="json"></result>
    </action>
    <action name="guardarUsuarioJson" class="Usuario" method="guardar">
        <result type="json"></result>
    </action>
</package>

<package name="utileriasSolosimpi" extends="struts-default, json-default">
    <action name="LoginSucessfull" class="ControlSesion" method="loginSuccesfull">
        <result>/test/MenuCatalogos.jsp</result>
    </action>
    <action name="MenuCatalogo" class="Navegacion" method="index">
        <result>/test/MenuCatalogos.jsp</result>
    </action>
</package>

<!--Para Direcciones JSON-->
<package name="direcciones" extends="struts-default, json-default">
    <action name="consultaCodigosPostalesPorLocalidadJson" class="Direcciones" method="consultarCodigosPostalesPorIdLocalidad">
        <result type="json"></result>
    </action>
    <action name="consultaColoniasPorCodigoPostalJson" class="Direcciones" method="consultarColoniasPorIdCodigoPostal">
        <result type="json"></result>
    </action>
    <action name="consultaEstadosPorPaisJson" class="Direcciones" method="consultarEstadosPorIdPais">
        <result type="json"></result>
    </action>
    <action name="consultaLocalidadesPorEstadoJson" class="Direcciones" method="consultarLocalidadesPorIdEstado">
        <result type="json"></result>
    </action>
    <action name="consultarPaisesJson" class="Direcciones" method="consultarPaises">
        <result type="json"></result>
    </action>
</package>

<package name="chat" extends="struts-default, json-default">
    <action name="consultarDestinatariosJson" class="Chat" method="consultarDestinatarios">
        <result type="json"></result>
    </action>
    <action name="consultarPropiedadesPorUsuarioJson" class="Chat" method="consultarPropiedadesPorIdUsuario">
        <result type="json"></result>
    </action>
    <action name="guardarMensajeJson" class="Chat" method="guardarMensaje">
        <result type="json"></result>
    </action>
    <action name="verChat" class="Chat" method="consultarMensajesPorIdUsuario">
        <result>/test/TestChat.jsp</result>
    </action>
    <action name="consultarMensajesJSON" class="Chat" method="consultarMensajesPorIdUsuario">
        <result type="json"></result>
    </action>
    <action name="consultarMensajesNoLeidosJSON" class="Chat" method="consultarMensajesNoLeidosPorIdUsuario">
        <result type="json"></result>
    </action>
    <action name="marcarMensaje" class="Chat" method="marcarMensaje">
        <result type="json"></result>
    </action>
</package>

<package name="busqueda" extends="struts-default, json-default">
    <action name="verBusqueda" class="Busqueda" method="mostrarPaginaBusqueda">
        <result>/test/TestBusqueda.jsp</result>
    </action>
    <action name="consultarPropiedadesPorPCJson" class="Busqueda" method="consultarPropiedadesPorLikeDescripcion">
        <result type="json"></result>
    </action>
    <action name="obtenerListaClaveJson" class="Busqueda" method="filtrarPalabrasClave">
        <result type="json"></result>
    </action>
    <action name="testURL" class="Navegacion" method="index">
        <result>/test/TestURL.jsp</result>
    </action>
</package>